bors/__init__.py
bors/algorithms/__init__.py
bors/algorithms/echo.py
bors/api/__init__.py
bors/api/base.py
bors/api/product.py
bors/api/requestor.py
bors/api/websock.py
bors/api/adapter/__init__.py
bors/api/adapter/api.py
bors/api/adapter/socketcluster.py
bors/app/__init__.py
bors/app/api_factory.py
bors/app/builder.py
bors/app/config.py
bors/app/log.py
bors/app/strategy.py
bors/common/__init__.py
bors/common/dict_merge.py
bors/common/dotobj.py
bors/common/factory.py
bors/common/singleton.py
bors/generics/__init__.py
bors/generics/api.py
bors/generics/common.py
bors/generics/config.py
bors/generics/context.py
bors/strategies/__init__.py
bors/strategies/echo.py
bors/strategies/print.py
bors-0.3.5.dist-info/METADATA
bors-0.3.5.dist-info/RECORD
bors-0.3.5.dist-info/WHEEL
bors-0.3.5.dist-info/top_level.txt
