Metadata-Version: 2.1
Name: bors
Version: 0.3.5
Summary: A highly flexible and extensible service integration framework for scraping the web or consuming APIs
Home-page: https://github.com/RobotStudio/bors
Author: Bobby
Author-email: bobby@robot.studio
License: GNU General Public License v3
Keywords: web-scraper api-integrator scraping scraper data-integration data-ingestion bors
Platform: UNKNOWN
Classifier: Development Status :: 2 - Pre-Alpha
Classifier: Intended Audience :: Developers
Classifier: License :: OSI Approved :: GNU General Public License v3 (GPLv3)
Classifier: Natural Language :: English
Classifier: Programming Language :: Python :: 3.6
Requires-Dist: dataclasses
Requires-Dist: marshmallow
Requires-Dist: requests
Requires-Dist: urllib3
